beautifultext/__init__.py
beautifultext/ansi.py
beautifultext/ansitowin32.py
beautifultext/initialise.py
beautifultext/win32.py
beautifultext/winterm.py
beautifultext/libs/__init__.py
beautifultext/libs/argparse.py
beautifultext/libs/os.py
beautifultext/libs/logging/__init__.py
beautifultext/libs/logging/config.py
beautifultext/libs/logging/handlers.py
beautifultext/libs/requests/__init__.py
beautifultext/libs/requests/__version__.py
beautifultext/libs/requests/_internal_utils.py
beautifultext/libs/requests/compat.py
beautifultext/libs/requests/cookies.py
beautifultext/libs/requests/exceptions.py
beautifultext/libs/requests/help.py
beautifultext/libs/requests/hooks.py
beautifultext/libs/requests/models.py
beautifultext/libs/requests/packages.py
beautifultext/libs/requests/sessions.py
beautifultext/libs/requests/status_codes.py
beautifultext/libs/requests/structures.py
beautifultext/libs/requests/utils.py
beautifultext/tests/__init__.py
beautifultext/tests/ansi_test.py
beautifultext/tests/ansitowin32_test.py
beautifultext/tests/initialise_test.py
beautifultext/tests/isatty_test.py
beautifultext/tests/utils.py
beautifultext/tests/winterm_test.py
beautifultext-0.0.1.dist-info/LICENSE.txt
beautifultext-0.0.1.dist-info/METADATA
beautifultext-0.0.1.dist-info/WHEEL
beautifultext-0.0.1.dist-info/top_level.txt
beautifultext-0.0.1.dist-info/RECORD
